yara_scanner.py
ysc.py
yss.py
yara_scanner-2.0.3.dist-info/entry_points.txt
yara_scanner-2.0.3.dist-info/LICENSE
yara_scanner-2.0.3.dist-info/WHEEL
yara_scanner-2.0.3.dist-info/METADATA
yara_scanner-2.0.3.dist-info/RECORD
