Metadata-Version: 2.1
Name: yara-scanner
Version: 2.0.3
Summary: A Python wrapper library for libyara and a local server for fully utilizing the CPUs of the system to scan with yara.
Home-page: https://github.com/ace-ecosystem/yara_scanner
License: Apache-2.0
Keywords: yara
Author: John Davison
Author-email: unixfreak0037@gmail.com
Requires-Python: >=3.7,<4.0
Classifier: Development Status :: 4 - Beta
Classifier: Intended Audience :: Developers
Classifier: Intended Audience :: Information Technology
Classifier: License :: OSI Approved :: Apache Software License
Classifier: Operating System :: OS Independent
Classifier: Programming Language :: Python :: 3
Classifier: Programming Language :: Python :: 3.10
Classifier: Programming Language :: Python :: 3.7
Classifier: Programming Language :: Python :: 3.8
Classifier: Programming Language :: Python :: 3.9
Requires-Dist: plyara (>=2.1.1,<3.0.0)
Requires-Dist: progress (>=1.5,<2.0)
Requires-Dist: psutil (>=5.6.7,<6.0.0)
Requires-Dist: yara-python (<4.1)
Project-URL: Repository, https://github.com/ace-ecosystem/yara_scanner
